summarizer/__init__.py
summarizer/graph.py
summarizer/main.py
summarizer/stuff.py
doc_summarizer-0.0.13.dist-info/METADATA
doc_summarizer-0.0.13.dist-info/WHEEL
doc_summarizer-0.0.13.dist-info/top_level.txt
doc_summarizer-0.0.13.dist-info/RECORD
