Metadata-Version: 2.4
Name: doc-summarizer
Version: 0.0.13
Summary: Text summarizer implemented via langchain.
Author-email: Hossein <hoseinshr1055@gmail.com>
Project-URL: Homepage, https://github.com/pypa/sampleproject
Classifier: Programming Language :: Python :: 3
Classifier: License :: OSI Approved :: MIT License
Classifier: Operating System :: OS Independent
Requires-Python: >=3.11
Requires-Dist: langchain
Requires-Dist: tiktoken
Requires-Dist: langgraph
Requires-Dist: beautifulsoup4
Requires-Dist: langchain-openai
Requires-Dist: langchain-community
Requires-Dist: unstructured
Requires-Dist: unstructured[docx,html]
Requires-Dist: pypdf
Requires-Dist: pdfplumber
Requires-Dist: python-docx
Requires-Dist: pandas
Requires-Dist: torch
Requires-Dist: torchvision
